vlcp_docker/__init__.py
vlcp_docker/cleanup.py
vlcp_docker/dockerplugin.py
vlcp_docker_plugin-0.3.0.dist-info/METADATA
vlcp_docker_plugin-0.3.0.dist-info/RECORD
vlcp_docker_plugin-0.3.0.dist-info/WHEEL
vlcp_docker_plugin-0.3.0.dist-info/top_level.txt
